that_ml_library/__init__.py
that_ml_library/_modidx.py
that_ml_library/chart_plotting.py
that_ml_library/data_preprocess.py
that_ml_library/ml_helpers.py
that_ml_library/utils.py
that_ml_library-0.0.6.dist-info/LICENSE
that_ml_library-0.0.6.dist-info/METADATA
that_ml_library-0.0.6.dist-info/WHEEL
that_ml_library-0.0.6.dist-info/entry_points.txt
that_ml_library-0.0.6.dist-info/top_level.txt
that_ml_library-0.0.6.dist-info/RECORD
