Metadata-Version: 2.1
Name: that-ml-library
Version: 0.0.6
Summary: A useful package for EDA and quick ML model building
Home-page: https://github.com/anhquan0412/that-ml-library
Author: Quan Tran
Author-email: anhquan0412@gmail.com
License: Apache Software License 2.0
Keywords: jupyter notebook python sklearn statistics statsmodels
Classifier: Development Status :: 4 - Beta
Classifier: Intended Audience :: Developers
Classifier: Natural Language :: English
Classifier: Programming Language :: Python :: 3.9
Classifier: Programming Language :: Python :: 3.10
Classifier: License :: OSI Approved :: Apache Software License
Requires-Python: >=3.9
License-File: LICENSE
Requires-Dist: numpy >=1.23.0
Requires-Dist: pandas >=1.5.0
Requires-Dist: scikit-learn >=1.2.0
Requires-Dist: matplotlib >=3.7.0
Requires-Dist: seaborn >=0.12.0
Requires-Dist: plotly >=5.14.0
Requires-Dist: dtreeviz >=2.2
Requires-Dist: statsmodels >=0.13.0
Requires-Dist: pingouin >=0.5.3
Requires-Dist: yellowbrick >=1.5
Provides-Extra: dev
